neuroprobe/__init__.py
neuroprobe/braintreebank_subject.py
neuroprobe/config.py
neuroprobe/datasets.py
neuroprobe/train_test_splits.py
neuroprobe/braintreebank_features_time_alignment/subject10_trial0_nonverbal_df.csv
neuroprobe/braintreebank_features_time_alignment/subject10_trial0_words_df.csv
neuroprobe/braintreebank_features_time_alignment/subject10_trial1_nonverbal_df.csv
neuroprobe/braintreebank_features_time_alignment/subject10_trial1_words_df.csv
neuroprobe/braintreebank_features_time_alignment/subject1_trial0_nonverbal_df.csv
neuroprobe/braintreebank_features_time_alignment/subject1_trial0_words_df.csv
neuroprobe/braintreebank_features_time_alignment/subject1_trial1_nonverbal_df.csv
neuroprobe/braintreebank_features_time_alignment/subject1_trial1_words_df.csv
neuroprobe/braintreebank_features_time_alignment/subject1_trial2_nonverbal_df.csv
neuroprobe/braintreebank_features_time_alignment/subject1_trial2_words_df.csv
neuroprobe/braintreebank_features_time_alignment/subject2_trial0_nonverbal_df.csv
neuroprobe/braintreebank_features_time_alignment/subject2_trial0_words_df.csv
neuroprobe/braintreebank_features_time_alignment/subject2_trial1_nonverbal_df.csv
neuroprobe/braintreebank_features_time_alignment/subject2_trial1_words_df.csv
neuroprobe/braintreebank_features_time_alignment/subject2_trial2_nonverbal_df.csv
neuroprobe/braintreebank_features_time_alignment/subject2_trial2_words_df.csv
neuroprobe/braintreebank_features_time_alignment/subject2_trial3_nonverbal_df.csv
neuroprobe/braintreebank_features_time_alignment/subject2_trial3_words_df.csv
neuroprobe/braintreebank_features_time_alignment/subject2_trial4_nonverbal_df.csv
neuroprobe/braintreebank_features_time_alignment/subject2_trial4_words_df.csv
neuroprobe/braintreebank_features_time_alignment/subject2_trial5_nonverbal_df.csv
neuroprobe/braintreebank_features_time_alignment/subject2_trial5_words_df.csv
neuroprobe/braintreebank_features_time_alignment/subject2_trial6_nonverbal_df.csv
neuroprobe-0.1.7.dist-info/licenses/LICENSE
neuroprobe-0.1.7.dist-info/METADATA
neuroprobe-0.1.7.dist-info/WHEEL
neuroprobe-0.1.7.dist-info/top_level.txt
neuroprobe-0.1.7.dist-info/RECORD
