Metadata-Version: 2.4
Name: neuroprobe
Version: 0.1.7
Summary: Neuroprobe: Benchmark for Evaluating iEEG Foundation Models. Evaluating intracranial brain responses to naturalistic stimuli.
Author: Andrii Zahorodnii, Christopher Wang, Bennett Stankovits, Charikleia Moraitaki, Geeling Chau, Andrei Barbu, Boris Katz, Ila R Fiete
License-Expression: MIT
Project-URL: Homepage, https://neuroprobe.dev
Project-URL: Repository, https://github.com/azaho/neuroprobe
Project-URL: Bug Reports, https://github.com/neuroprobe/neuroprobe/issues
Keywords: neuroscience,brain,neural-data,benchmark,intracranial,eeg,ieeg,seeg,ecog,foundation-models,evaluation,naturalistic-stimuli,machine-learning,pytorch
Classifier: Development Status :: 4 - Beta
Classifier: Intended Audience :: Science/Research
Classifier: Operating System :: OS Independent
Classifier: Programming Language :: Python :: 3
Classifier: Programming Language :: Python :: 3.8
Classifier: Programming Language :: Python :: 3.9
Classifier: Programming Language :: Python :: 3.10
Classifier: Programming Language :: Python :: 3.11
Classifier: Programming Language :: Python :: 3.12
Classifier: Topic :: Scientific/Engineering :: Artificial Intelligence
Classifier: Topic :: Scientific/Engineering :: Medical Science Apps.
Classifier: Topic :: Scientific/Engineering :: Information Analysis
Classifier: Topic :: Software Development :: Libraries :: Python Modules
Requires-Python: >=3.8
License-File: LICENSE
Requires-Dist: torch
Requires-Dist: torchvision
Requires-Dist: h5py
Requires-Dist: pandas
Requires-Dist: numpy
Requires-Dist: scipy
Requires-Dist: scikit-learn
Requires-Dist: matplotlib
Requires-Dist: seaborn
Requires-Dist: psutil
Requires-Dist: scikit-learn
Provides-Extra: dev
Requires-Dist: beautifulsoup4; extra == "dev"
Requires-Dist: requests; extra == "dev"
Requires-Dist: jupyter; extra == "dev"
Requires-Dist: ipykernel; extra == "dev"
Requires-Dist: matplotlib; extra == "dev"
Requires-Dist: seaborn; extra == "dev"
Requires-Dist: psutil; extra == "dev"
Dynamic: license-file
